{
    "ability":
    {
        "archery": { "name": "Archery" },
        "athletics": { "name": "Athletics" },
        "awareness": { "name": "Awareness" },
        "bureaucracy": { "name": "Bureaucracy" },
        "craft": { "name": "Craft" },
        "dodge": { "name": "Dodge" },
        "integrity": { "name": "Integrity" },
        "investigation": { "name": "Investigation" },
        "larceny": { "name": "Larceny" },
        "linguistics": { "name": "Linguistics" },
        "lore": { "name": "Lore" },
        "martialarts": { "name": "Martial Arts" },
        "medicine": { "name": "Medicine" },
        "melee": { "name": "Melee" },
        "occult": { "name": "Occult" },
        "performance": { "name": "Performance" },
        "presence": { "name": "Presence" },
        "resistance": { "name": "Resistance" },
        "ride": { "name": "Ride" },
        "sail": { "name": "Sail" },
        "socialise": { "name": "Socialise" },
        "stealth": { "name": "Stealth" },
        "survival": { "name": "Survival" },
        "thrown": { "name": "Thrown" },
        "war": { "name": "War" }
    },
    "skill":
    {
        "sleeping": { "name": "Sleeping" },
        "farming": { "name": "Farming" },
        "toughness": { "name": "Toughness" },
        "timekeeping": { "name": "Timekeeping" }
    },
    "perk":
    {
        "timekeeping.time_display": "Can see exact time of day",
        "timekeeping.dayofweek_display": "Can see current day of week",
        "timekeeping.month_display": "Can see current month",
        "timekeeping.dayofmonth_display": "Can see exact day in the month",
        "timekeeping.year_display": "Can see current year"
    },
    "test": "dongs"
}